Classfile /Users/bertking/IdeaProjects/src/jvm/descriptors.MethodDescriptions.class
  Last modified 2020年8月3日; size 376 bytes
  SHA-256 checksum ad419ef323952fe0b47351b3509719ff248546a0c679fbf678a321275c1030aa
  Compiled from "descriptors.MethodDescriptions.java"
public class jvm.descriptors.MethodDescriptions
  minor version: 0
  major version: 57
  flags: (0x0021) ACC_PUBLIC, ACC_SUPER
  this_class: #9                          // jvm/descriptors.MethodDescriptions
  super_class: #2                         // java/lang/Object
  interfaces: 0, fields: 0, methods: 3, attributes: 1
Constant pool:
   #1 = Methodref          #2.#3          // java/lang/Object."<init>":()V
   #2 = Class              #4             // java/lang/Object
   #3 = NameAndType        #5:#6          // "<init>":()V
   #4 = Utf8               java/lang/Object
   #5 = Utf8               <init>
   #6 = Utf8               ()V
   #7 = String             #8             // Bertking
   #8 = Utf8               Bertking
   #9 = Class              #10            // jvm/descriptors.MethodDescriptions
  #10 = Utf8               jvm/descriptors.MethodDescriptions
  #11 = Utf8               Code
  #12 = Utf8               LineNumberTable
  #13 = Utf8               showTime
  #14 = Utf8               getName
  #15 = Utf8               (Ljava/lang/String;ZI)Ljava/lang/String;
  #16 = Utf8               SourceFile
  #17 = Utf8               descriptors.MethodDescriptions.java
{
  public jvm.descriptors.MethodDescriptions();
    descriptor: ()V // 默认的无参构造函数，无参且无返回值，故这里为()V
    flags: (0x0001) ACC_PUBLIC
    Code:
      stack=1, locals=1, args_size=1
         0: aload_0
         1: invokespecial #1                  // Method java/lang/Object."<init>":()V
         4: return
      LineNumberTable:
        line 11: 0
        line 12: 4

  public void showTime();
    descriptor: ()V  // 这里的无参，所以没有参数描述符;ZI,且该函数无返回值，So返回值描述符为V
    flags: (0x0001) ACC_PUBLIC
    Code:
      stack=0, locals=1, args_size=1
         0: return
      LineNumberTable:
        line 16: 0

  public java.lang.String getName(java.lang.String, boolean, int);
    descriptor: (Ljava/lang/String;ZI)Ljava/lang/String; // 这里的参数描述符为Ljava/lang/String;ZI,而返回值描述符为Ljava/lang/String
    flags: (0x0001) ACC_PUBLIC
    Code:
      stack=1, locals=4, args_size=4
         0: ldc           #7                  // String Bertking
         2: areturn
      LineNumberTable:
        line 19: 0
}
SourceFile: "descriptors.MethodDescriptions.java"
